waifus/__init__.py
waifus-1.0.0.dist-info/LICENSE
waifus-1.0.0.dist-info/METADATA
waifus-1.0.0.dist-info/WHEEL
waifus-1.0.0.dist-info/top_level.txt
waifus-1.0.0.dist-info/RECORD
