Metadata-Version: 2.1
Name: waifus
Version: 1.0.0
Summary: getting some waifu pics
Home-page: https://github.com/phoenixthrush-develops/waifus
Author: Phoenixthrush UwU
Author-email: <contact@phoenixthrush.com>
License: UNKNOWN
Project-URL: Bug Tracker, https://github.com/phoenixthrush-develops/waifus/issues
Keywords: waifus,python,package,library,lib,module
Platform: UNKNOWN
Classifier: Intended Audience :: Developers
Classifier: Programming Language :: Python :: 3
Classifier: License :: OSI Approved :: MIT License
Classifier: Operating System :: OS Independent
License-File: LICENSE
Requires-Dist: argparse
Requires-Dist: requests
Requires-Dist: tk
Requires-Dist: Pillow
